kiri_pathfinding/__init__.py
kiri_pathfinding/map_generator.py
kiri_pathfinding/pathfinding.py
kiri_pathfinding-1.2.0.dist-info/LICENSE
kiri_pathfinding-1.2.0.dist-info/WHEEL
kiri_pathfinding-1.2.0.dist-info/METADATA
kiri_pathfinding-1.2.0.dist-info/RECORD
