Metadata-Version: 2.1
Name: kiri-pathfinding
Version: 1.2.0
Summary: A toy module to generate a map and find the shortest path from two points on the map
Home-page: https://github.com/kiri-chow/kiri-pathfinding
License: MIT
Author: anthony
Author-email: mrchowpoor@gmail.com
Requires-Python: >=3.9,<4.0
Classifier: License :: OSI Approved :: MIT License
Classifier: Programming Language :: Python :: 3
Classifier: Programming Language :: Python :: 3.9
Classifier: Programming Language :: Python :: 3.10
Classifier: Programming Language :: Python :: 3.11
Requires-Dist: matplotlib (>=3.6.1,<4.0.0)
Requires-Dist: numba (>=0.56.3,<0.57.0)
Requires-Dist: numpy (>=1.23.4,<2.0.0)
Requires-Dist: scikit-image (>=0.19.3,<0.20.0)
Requires-Dist: scikit-learn (>=1.1.2,<2.0.0)
Project-URL: Repository, https://github.com/kiri-chow/kiri-pathfinding
